mm1_torch/__init__.py
mm1_torch/main.py
mm1_torch/resblock_text.py
mm1_torch-0.0.6.dist-info/LICENSE
mm1_torch-0.0.6.dist-info/WHEEL
mm1_torch-0.0.6.dist-info/METADATA
mm1_torch-0.0.6.dist-info/RECORD
